curslibm/__init__.py
curslibm/database.py
curslibm-0.1.dist-info/METADATA
curslibm-0.1.dist-info/WHEEL
curslibm-0.1.dist-info/top_level.txt
curslibm-0.1.dist-info/RECORD
