Metadata-Version: 2.1
Name: curslibm
Version: 0.1
Summary: A library for interacting with a PostgreSQL database
Home-page: https://github.com/yourusername/curslibm
Author: Your Name
Author-email: your.email@example.com
Classifier: Programming Language :: Python :: 3
Classifier: License :: OSI Approved :: MIT License
Classifier: Operating System :: OS Independent
Requires-Python: >=3.6
Requires-Dist: psycopg2
